oddevengame/__init__.py
oddevengame/oddevengame.py
OddEvenGame-0.0.15.dist-info/LICENSE
OddEvenGame-0.0.15.dist-info/METADATA
OddEvenGame-0.0.15.dist-info/WHEEL
OddEvenGame-0.0.15.dist-info/top_level.txt
OddEvenGame-0.0.15.dist-info/RECORD
