Metadata-Version: 2.1
Name: OddEvenGame
Version: 0.0.15
Summary: A fun and interactive Odd-Even cricket game where you play against the computer.
Home-page: https://github.com/siddharthdis/OddEvenGame
Author: Siddharth Yadav
Author-email: siddharthdis3432@gmail.com
License: MIT License
Keywords: OddEvenGame,Odd Even Game,Cricket Game,Odd Even,Python Game,Interactive Game,Siddharth Yadav
Classifier: Development Status :: 4 - Beta
Classifier: Intended Audience :: Developers
Classifier: Intended Audience :: End Users/Desktop
Classifier: License :: OSI Approved :: MIT License
Classifier: Natural Language :: English
Classifier: Operating System :: OS Independent
Classifier: Programming Language :: Python :: 3
Classifier: Programming Language :: Python :: 3.8
Classifier: Programming Language :: Python :: 3.9
Classifier: Programming Language :: Python :: 3.10
Classifier: Programming Language :: Python :: 3.11
Classifier: Topic :: Games/Entertainment :: Simulation
Classifier: Topic :: Software Development :: Libraries :: Python Modules
Requires-Python: >=3.8
License-File: LICENSE
